MANIFEST.in
README.md
setup.py
django_lastfmauth.egg-info/PKG-INFO
django_lastfmauth.egg-info/SOURCES.txt
django_lastfmauth.egg-info/dependency_links.txt
django_lastfmauth.egg-info/not-zip-safe
django_lastfmauth.egg-info/top_level.txt
docs/index.rst
docs/usage.rst
lastfmauth/__init__.py
lastfmauth/admin.py
lastfmauth/backends.py
lastfmauth/models.py
lastfmauth/tests.py
lastfmauth/urls.py
lastfmauth/views.py