Metadata-Version: 1.0
Name: django-lastfmauth
Version: 0.1a2
Summary: Django app to let your website visitors register/login using LastFM authentication webservice.
Home-page: http://github.com/matagus/django-lastfm-auth
Author: Matias Agustin Mendez
Author-email: me@matagus.com.ar
License: MIT
Platform: UNKNOWN
Classifier: Development Status :: 3 - Alpha
Classifier: Framework :: Django
Classifier: Intended Audience :: Developers
Classifier: License :: OSI Approved :: MIT License
Classifier: Operating System :: OS Independent
Classifier: Programming Language :: Python
Classifier: Programming Language :: Python :: 2.6
Classifier: Topic :: Internet :: WWW/HTTP
